python_aitest_writer/__init__.py
python_aitest_writer/generate_test_cases.py
python_aitest_writer-0.1.0.dist-info/METADATA
python_aitest_writer-0.1.0.dist-info/WHEEL
python_aitest_writer-0.1.0.dist-info/entry_points.txt
python_aitest_writer-0.1.0.dist-info/top_level.txt
python_aitest_writer-0.1.0.dist-info/RECORD
