Metadata-Version: 2.1
Name: python-aitest-writer
Version: 0.1.0
Summary: Generate pytest test cases for your Python app using Claude AI
Home-page: https://github.com/yourusername/python_aitest_writer
Author: Your Name
Author-email: your.email@example.com
License: UNKNOWN
Platform: UNKNOWN
Classifier: Programming Language :: Python :: 3
Classifier: License :: OSI Approved :: MIT License
Classifier: Operating System :: OS Independent
Requires-Python: >=3.7
Requires-Dist: pytest
Requires-Dist: requests
